henry_sdk/__init__.py
henry_sdk/_base_client.py
henry_sdk/_client.py
henry_sdk/_compat.py
henry_sdk/_constants.py
henry_sdk/_exceptions.py
henry_sdk/_files.py
henry_sdk/_models.py
henry_sdk/_qs.py
henry_sdk/_resource.py
henry_sdk/_response.py
henry_sdk/_streaming.py
henry_sdk/_types.py
henry_sdk/_version.py
henry_sdk/py.typed
henry_sdk/_utils/__init__.py
henry_sdk/_utils/_compat.py
henry_sdk/_utils/_datetime_parse.py
henry_sdk/_utils/_logs.py
henry_sdk/_utils/_proxy.py
henry_sdk/_utils/_reflection.py
henry_sdk/_utils/_resources_proxy.py
henry_sdk/_utils/_streams.py
henry_sdk/_utils/_sync.py
henry_sdk/_utils/_transform.py
henry_sdk/_utils/_typing.py
henry_sdk/_utils/_utils.py
henry_sdk/lib/.keep
henry_sdk/resources/__init__.py
henry_sdk/resources/merchants.py
henry_sdk/resources/orders.py
henry_sdk/resources/wallet.py
henry_sdk/resources/cart/__init__.py
henry_sdk/resources/cart/cart.py
henry_sdk/resources/cart/items.py
henry_sdk/resources/checkout/__init__.py
henry_sdk/resources/checkout/checkout.py
henry_sdk/resources/checkout/session.py
henry_sdk/resources/products/__init__.py
henry_sdk/resources/products/products.py
henry_sdk/resources/products/variant_check.py
henry_sdk/types/__init__.py
henry_sdk/types/cart_create_checkout_params.py
henry_sdk/types/cart_create_checkout_response.py
henry_sdk/types/merchant_check_status_params.py
henry_sdk/types/merchant_check_status_response.py
henry_sdk/types/merchant_get_shipping_info_params.py
henry_sdk/types/merchant_get_shipping_info_response.py
henry_sdk/types/merchant_list_supported_params.py
henry_sdk/types/merchant_list_supported_response.py
henry_sdk/types/order_retrieve_status_response.py
henry_sdk/types/product_retrieve_details_params.py
henry_sdk/types/product_retrieve_details_response.py
henry_sdk/types/product_search_params.py
henry_sdk/types/product_search_response.py
henry_sdk/types/wallet_create_card_collection_params.py
henry_sdk/types/wallet_create_card_collection_response.py
henry_sdk/types/cart/__init__.py
henrylabs-0.2.0.dist-info/METADATA
henrylabs-0.2.0.dist-info/WHEEL
henrylabs-0.2.0.dist-info/licenses/LICENSE
henrylabs-0.2.0.dist-info/RECORD
